{
	"name": "dataflow3",
	"properties": {
		"type": "MappingDataFlow",
		"typeProperties": {
			"sources": [
				{
					"dataset": {
						"referenceName": "DS_conditionalsplitinput",
						"type": "DatasetReference"
					},
					"name": "source1"
				}
			],
			"sinks": [
				{
					"dataset": {
						"referenceName": "ds_outputconditionalsplitdataflow",
						"type": "DatasetReference"
					},
					"name": "sink1"
				}
			],
			"transformations": [],
			"scriptLines": [
				"source(output(",
				"          transaction_id as string,",
				"          city as string,",
				"          transaction_date as string,",
				"          card_type as string,",
				"          exp_type as string,",
				"          gender as string,",
				"          amount as string",
				"     ),",
				"     allowSchemaDrift: true,",
				"     validateSchema: false,",
				"     inferDriftedColumnTypes: true,",
				"     ignoreNoFilesFound: false,",
				"     partitionBy('hash', 2,",
				"          card_type",
				"     )) ~> source1",
				"source1 sink(allowSchemaDrift: true,",
				"     validateSchema: false,",
				"     umask: 0022,",
				"     preCommands: [],",
				"     postCommands: [],",
				"     skipDuplicateMapInputs: true,",
				"     skipDuplicateMapOutputs: true) ~> sink1"
			]
		}
	}
}